discord/ext/levenshtein/__init__.py
discord/ext/levenshtein/inner_cog.py
discord_ext_levenshtein-0.3.0.dist-info/LICENSE
discord_ext_levenshtein-0.3.0.dist-info/METADATA
discord_ext_levenshtein-0.3.0.dist-info/WHEEL
discord_ext_levenshtein-0.3.0.dist-info/top_level.txt
discord_ext_levenshtein-0.3.0.dist-info/RECORD
