Metadata-Version: 2.1
Name: discord-ext-levenshtein
Version: 0.3.0
Summary: A discord.py extension for command name suggestion
Home-page: https://github.com/shirataki2/discord-ext-levenshtein
Author: Shirataki2
Author-email: tmy1997530@gmail.com
License: MIT
Project-URL: Documentation, https://discord-ext-levenshtein.readthedocs.io/en/latest/
Project-URL: Source, https://github.com/shirataki2/discord-ext-levenshtein
Project-URL: Tracker, https://github.com/Shirataki2/discord-ext-levenshtein/issues
Platform: UNKNOWN
Classifier: Development Status :: 3 - Alpha
Classifier: Intended Audience :: Developers
Classifier: License :: OSI Approved :: MIT License
Classifier: Natural Language :: English
Classifier: Operating System :: OS Independent
Classifier: Programming Language :: Python :: 3
Classifier: Programming Language :: Python :: 3 :: Only
Classifier: Programming Language :: Python :: 3.6
Classifier: Programming Language :: Python :: 3.7
Classifier: Programming Language :: Python :: 3.8
Classifier: Programming Language :: Python :: 3.9
Classifier: Programming Language :: Python :: Implementation :: CPython
Classifier: Topic :: Software Development
Classifier: Topic :: Software Development :: Libraries :: Python Modules
Requires-Python: >=3.6.0
Requires-Dist: discord.py
Requires-Dist: python-Levenshtein
Provides-Extra: docs
Requires-Dist: sphinx ; extra == 'docs'
Requires-Dist: sphinxcontrib-trio ; extra == 'docs'
Requires-Dist: sphinxcontrib-websupport ; extra == 'docs'
Requires-Dist: sphinx-rtd-theme ; extra == 'docs'
